dotsplit/__init__.py
dotsplit/dotsplit.py
dotsplit-0.2.1.dist-info/LICENSE
dotsplit-0.2.1.dist-info/WHEEL
dotsplit-0.2.1.dist-info/METADATA
dotsplit-0.2.1.dist-info/RECORD
