Metadata-Version: 2.1
Name: dotsplit
Version: 0.2.1
Summary: Transform dot-delimited strings to an array of python strings.
Home-page: https://github.com/wilmoore/dotsplit.py
Keywords: array,dot,namespace,split,string
Author: Deyon Samuel Washington
Author-email: winnersonly@realpolyglot.com
Requires-Python: >=3.8,<4.0
Classifier: Programming Language :: Python :: 3
Classifier: Programming Language :: Python :: 3.8
Classifier: Programming Language :: Python :: 3.9
Project-URL: Repository, https://github.com/wilmoore/dotsplit.py
